setup.py
accounts/__init__.py
accounts/admin.py
accounts/api.py
accounts/models.py
accounts/tests.py
accounts/urls.py
accounts/views.py
django_luoji_accounts.egg-info/PKG-INFO
django_luoji_accounts.egg-info/SOURCES.txt
django_luoji_accounts.egg-info/dependency_links.txt
django_luoji_accounts.egg-info/not-zip-safe
django_luoji_accounts.egg-info/top_level.txt