Metadata-Version: 1.1
Name: django-luoji-accounts
Version: 0.0.2
Summary: A general account app for projects
Home-page: https://github.com/hereischen/django-luoji-accounts
Author: Haotong Chen
Author-email: hereischen@gmail.com
License: BSD License
Platform: UNKNOWN
Classifier: Development Status :: 5 - Production/Stable
Classifier: Intended Audience :: Developers
Classifier: Topic :: Software Development :: Build Tools
Classifier: License :: OSI Approved :: BSD License
Classifier: Programming Language :: Python :: 2.7
